dunglaierrors/__init__.py
dunglaierrors-0.0.7.dist-info/LICENSE
dunglaierrors-0.0.7.dist-info/METADATA
dunglaierrors-0.0.7.dist-info/WHEEL
dunglaierrors-0.0.7.dist-info/top_level.txt
dunglaierrors-0.0.7.dist-info/RECORD
