Metadata-Version: 2.1
Name: dunglaierrors
Version: 0.0.7
Summary: Detect Dung Lai's common errors
Home-page: https://github.com/MHP0920/dunglaierror
Author: MHP
Author-email: admin@hieudeeptry.ml
License: MIT
Keywords: dunglai,error,python,python3
Classifier: Programming Language :: Python :: 3
Classifier: License :: OSI Approved :: MIT License
Classifier: Operating System :: OS Independent
Requires-Python: >=3.6
License-File: LICENSE
Requires-Dist: colorama
